<?xml version="1.0" encoding="utf-8"?>
<Jobs>
  <ApplicationJob xmlns:xsi="http://www.w3.org/2001/XMLSchema-instance" xmlns:xsd="http://www.w3.org/2001/XMLSchema" Guid="7451ceae-c0a0-4a79-9706-994225a7a3eb">
    <WebsiteUrl />
    <UserAgent />
    <UserNotes />
    <LastFileSize>53248</LastFileSize>
    <LastFileDate>2016-02-04T19:36:44.8086416</LastFileDate>
    <IgnoreFileInformation>false</IgnoreFileInformation>
    <DownloadBeta>Default</DownloadBeta>
    <DownloadDate xsi:nil="true" />
    <CheckForUpdatesOnly>false</CheckForUpdatesOnly>
    <VariableChangeIndicator />
    <HashType>None</HashType>
    <CanBeShared>true</CanBeShared>
    <ShareApplication>false</ShareApplication>
    <ExclusiveDownload>false</ExclusiveDownload>
    <HttpReferer />
    <SetupInstructions />
    <Variables>
      <item>
        <key>
          <string>url</string>
        </key>
        <value>
          <UrlVariable>
            <RegexRightToLeft>false</RegexRightToLeft>
            <VariableType>Textual</VariableType>
            <Regex />
            <TextualContent>http://www.sentex.net/%7Emwandel/finddupe/finddupe.exe</TextualContent>
            <Name>url</Name>
          </UrlVariable>
        </value>
      </item>
      <item>
        <key>
          <string>version</string>
        </key>
        <value>
          <UrlVariable>
            <RegexRightToLeft>false</RegexRightToLeft>
            <VariableType>RegularExpression</VariableType>
            <Regex>(?&lt;=Version\s)([\d\.]+)(?=\s+)</Regex>
            <Url>http://www.sentex.net/%7Emwandel/finddupe/</Url>
            <Name>version</Name>
          </UrlVariable>
        </value>
      </item>
      <item>
        <key>
          <string>nopush</string>
        </key>
        <value>
          <UrlVariable>
            <RegexRightToLeft>false</RegexRightToLeft>
            <VariableType>Textual</VariableType>
            <Regex />
            <TextualContent>--nopush</TextualContent>
            <Name>nopush</Name>
          </UrlVariable>
        </value>
      </item>
      <item>
        <key>
          <string>cscript</string>
        </key>
        <value>
          <UrlVariable>
            <RegexRightToLeft>false</RegexRightToLeft>
            <VariableType>Textual</VariableType>
            <Regex />
            <TextualContent>2</TextualContent>
            <Name>cscript</Name>
          </UrlVariable>
        </value>
      </item>
    </Variables>
    <ExecuteCommand />
    <ExecutePreCommand />
    <ExecuteCommandType>Batch</ExecuteCommandType>
    <ExecutePreCommandType>Batch</ExecutePreCommandType>
    <Category />
    <SourceType>FixedUrl</SourceType>
    <PreviousLocation>F:\exe\finddupe.exe</PreviousLocation>
    <DeletePreviousFile>false</DeletePreviousFile>
    <Enabled>true</Enabled>
    <FileHippoId />
    <LastUpdated>2016-02-04T19:36:44.8086416</LastUpdated>
    <TargetPath>{workdir}\</TargetPath>
    <FixedDownloadUrl>{url}</FixedDownloadUrl>
    <Name>finddupe</Name>
  </ApplicationJob>
</Jobs>