<?xml version="1.0" encoding="utf-8"?>
<Jobs>
  <ApplicationJob xmlns:xsi="http://www.w3.org/2001/XMLSchema-instance" xmlns:xsd="http://www.w3.org/2001/XMLSchema" Guid="29397a2b-ebf4-4993-854a-f24449db3880">
    <WebsiteUrl />
    <UserAgent />
    <UserNotes />
    <LastFileSize>21834752</LastFileSize>
    <LastFileDate>2016-02-04T18:06:05.7488824</LastFileDate>
    <IgnoreFileInformation>false</IgnoreFileInformation>
    <DownloadBeta>Default</DownloadBeta>
    <DownloadDate xsi:nil="true" />
    <CheckForUpdatesOnly>false</CheckForUpdatesOnly>
    <VariableChangeIndicator />
    <HashType>None</HashType>
    <CanBeShared>true</CanBeShared>
    <ShareApplication>false</ShareApplication>
    <ExclusiveDownload>false</ExclusiveDownload>
    <HttpReferer />
    <SetupInstructions />
    <Variables>
      <item>
        <key>
          <string>nopush</string>
        </key>
        <value>
          <UrlVariable>
            <RegexRightToLeft>false</RegexRightToLeft>
            <VariableType>Textual</VariableType>
            <Regex />
            <TextualContent>--nopush</TextualContent>
            <Name>nopush</Name>
          </UrlVariable>
        </value>
      </item>
      <item>
        <key>
          <string>version</string>
        </key>
        <value>
          <UrlVariable>
            <RegexRightToLeft>false</RegexRightToLeft>
            <VariableType>RegularExpression</VariableType>
            <Regex>files/pydio-sync/java/([\d\.]+)</Regex>
            <Url>https://sourceforge.net/projects/ajaxplorer/files/pydio-sync/java/0.8.4/</Url>
            <Name>version</Name>
          </UrlVariable>
        </value>
      </item>
      <item>
        <key>
          <string>url</string>
        </key>
        <value>
          <UrlVariable>
            <RegexRightToLeft>false</RegexRightToLeft>
            <VariableType>Textual</VariableType>
            <Regex />
            <Url />
            <TextualContent>{getMirror}/{getUrl:regex:pydio\-sync.*(?=/download)}</TextualContent>
            <Name>url</Name>
          </UrlVariable>
        </value>
      </item>
      <item>
        <key>
          <string>url64</string>
        </key>
        <value>
          <UrlVariable>
            <RegexRightToLeft>false</RegexRightToLeft>
            <VariableType>Textual</VariableType>
            <Regex />
            <TextualContent>{urlArray}</TextualContent>
            <Name>url64</Name>
          </UrlVariable>
        </value>
      </item>
      <item>
        <key>
          <string>getUrl</string>
        </key>
        <value>
          <UrlVariable>
            <RegexRightToLeft>false</RegexRightToLeft>
            <VariableType>RegularExpression</VariableType>
            <Regex>[^ "'&lt;&gt;\*]+86-Setup\.msi/download</Regex>
            <Url>https://sourceforge.net/projects/ajaxplorer/files/pydio-sync/java/{version}/</Url>
            <Name>getUrl</Name>
          </UrlVariable>
        </value>
      </item>
      <item>
        <key>
          <string>getUrl64</string>
        </key>
        <value>
          <UrlVariable>
            <RegexRightToLeft>false</RegexRightToLeft>
            <VariableType>RegularExpression</VariableType>
            <Regex>[^ "'&lt;&gt;\*]+64-Setup\.msi/download</Regex>
            <Url>https://sourceforge.net/projects/ajaxplorer/files/pydio-sync/java/{version}/</Url>
            <Name>getUrl64</Name>
          </UrlVariable>
        </value>
      </item>
      <item>
        <key>
          <string>checksum64file</string>
        </key>
        <value>
          <UrlVariable>
            <RegexRightToLeft>false</RegexRightToLeft>
            <VariableType>Textual</VariableType>
            <Regex />
            <TextualContent>{getMirror}/{getUrl64:regex:pydio\-sync.*(?=/download)}</TextualContent>
            <Name>checksum64file</Name>
          </UrlVariable>
        </value>
      </item>
      <item>
        <key>
          <string>getUrlZip</string>
        </key>
        <value>
          <UrlVariable>
            <RegexRightToLeft>false</RegexRightToLeft>
            <VariableType>RegularExpression</VariableType>
            <Regex>[^ "'&lt;&gt;\*]+\.zip/download</Regex>
            <Url>https://sourceforge.net/projects/ajaxplorer/files/pydio-sync/java/{version}/</Url>
            <Name>getUrlZip</Name>
          </UrlVariable>
        </value>
      </item>
      <item>
        <key>
          <string>getMirror</string>
        </key>
        <value>
          <UrlVariable>
            <RegexRightToLeft>false</RegexRightToLeft>
            <VariableType>RegularExpression</VariableType>
            <Regex>(?&lt;=ResponseUri: )[^\r\n]+(?=/pydio-sync/)</Regex>
            <Url>{getUrlZip}</Url>
            <Name>getMirror</Name>
          </UrlVariable>
        </value>
      </item>
      <item>
        <key>
          <string>urlArray</string>
        </key>
        <value>
          <UrlVariable>
            <RegexRightToLeft>false</RegexRightToLeft>
            <VariableType>Textual</VariableType>
            <Regex />
            <TextualContent>@('{getUrl}', '{getUrl64}')</TextualContent>
            <Name>urlArray</Name>
          </UrlVariable>
        </value>
      </item>
      <item>
        <key>
          <string>cscript</string>
        </key>
        <value>
          <UrlVariable>
            <RegexRightToLeft>false</RegexRightToLeft>
            <VariableType>Textual</VariableType>
            <Regex />
            <TextualContent>2</TextualContent>
            <Name>cscript</Name>
          </UrlVariable>
        </value>
      </item>
    </Variables>
    <ExecuteCommand />
    <ExecutePreCommand />
    <ExecuteCommandType>Batch</ExecuteCommandType>
    <ExecutePreCommandType>Batch</ExecutePreCommandType>
    <Category />
    <SourceType>FixedUrl</SourceType>
    <PreviousLocation>F:\exe\Pydio-0.8.4-Windows-x86-Setup.msi</PreviousLocation>
    <DeletePreviousFile>false</DeletePreviousFile>
    <Enabled>true</Enabled>
    <FileHippoId />
    <LastUpdated>2016-02-04T18:06:05.7488824</LastUpdated>
    <TargetPath>{workdir}\</TargetPath>
    <FixedDownloadUrl>{url}</FixedDownloadUrl>
    <Name>pydio-sync</Name>
  </ApplicationJob>
</Jobs>