<?xml version="1.0" encoding="utf-8"?>
<Jobs>
  <ApplicationJob xmlns:xsi="http://www.w3.org/2001/XMLSchema-instance" xmlns:xsd="http://www.w3.org/2001/XMLSchema" Guid="73b90799-8d6b-4f2c-b551-163dd3854e54">
    <WebsiteUrl />
    <UserAgent />
    <UserNotes />
    <LastFileSize>5186991</LastFileSize>
    <LastFileDate>2016-02-13T14:11:08.6049833</LastFileDate>
    <IgnoreFileInformation>false</IgnoreFileInformation>
    <DownloadBeta>Default</DownloadBeta>
    <DownloadDate xsi:nil="true" />
    <CheckForUpdatesOnly>false</CheckForUpdatesOnly>
    <VariableChangeIndicator />
    <HashType>None</HashType>
    <CanBeShared>true</CanBeShared>
    <ShareApplication>false</ShareApplication>
    <ExclusiveDownload>false</ExclusiveDownload>
    <HttpReferer />
    <SetupInstructions />
    <Variables>
      <item>
        <key>
          <string>nopush</string>
        </key>
        <value>
          <UrlVariable>
            <RegexRightToLeft>false</RegexRightToLeft>
            <VariableType>Textual</VariableType>
            <Regex />
            <TextualContent>--nopush</TextualContent>
            <Name>nopush</Name>
          </UrlVariable>
        </value>
      </item>
      <item>
        <key>
          <string>version</string>
        </key>
        <value>
          <UrlVariable>
            <RegexRightToLeft>false</RegexRightToLeft>
            <VariableType>RegularExpression</VariableType>
            <Regex>(?&lt;=Current Version: )[\d\.]+</Regex>
            <Url>http://legroom.net/software/uniextract</Url>
            <Name>version</Name>
          </UrlVariable>
        </value>
      </item>
      <item>
        <key>
          <string>url</string>
        </key>
        <value>
          <UrlVariable>
            <RegexRightToLeft>false</RegexRightToLeft>
            <VariableType>Textual</VariableType>
            <Regex />
            <TextualContent>{host}/{urlPath}</TextualContent>
            <Name>url</Name>
          </UrlVariable>
        </value>
      </item>
      <item>
        <key>
          <string>urlPath</string>
        </key>
        <value>
          <UrlVariable>
            <RegexRightToLeft>false</RegexRightToLeft>
            <VariableType>RegularExpression</VariableType>
            <Regex>[^ "'&lt;&gt;\*]+{version:replace:.:}_noinst</Regex>
            <Url>http://legroom.net/software/uniextract</Url>
            <Name>urlPath</Name>
          </UrlVariable>
        </value>
      </item>
      <item>
        <key>
          <string>host</string>
        </key>
        <value>
          <UrlVariable>
            <RegexRightToLeft>false</RegexRightToLeft>
            <VariableType>Textual</VariableType>
            <Regex />
            <Url />
            <TextualContent>http://legroom.net/</TextualContent>
            <Name>host</Name>
          </UrlVariable>
        </value>
      </item>
      <item>
        <key>
          <string>cscript</string>
        </key>
        <value>
          <UrlVariable>
            <RegexRightToLeft>false</RegexRightToLeft>
            <VariableType>Textual</VariableType>
            <Regex />
            <TextualContent>2</TextualContent>
            <Name>cscript</Name>
          </UrlVariable>
        </value>
      </item>
      <item>
        <key>
          <string>packageGuid</string>
        </key>
        <value>
          <UrlVariable>
            <RegexRightToLeft>false</RegexRightToLeft>
            <VariableType>Textual</VariableType>
            <Regex />
            <Url />
            <TextualContent>{host}/{urlSrc}</TextualContent>
            <Name>packageGuid</Name>
          </UrlVariable>
        </value>
      </item>
      <item>
        <key>
          <string>urlSrc</string>
        </key>
        <value>
          <UrlVariable>
            <RegexRightToLeft>false</RegexRightToLeft>
            <VariableType>RegularExpression</VariableType>
            <Regex>/?([^ "'&lt;&gt;\*]+{version:replace:.:}_source)</Regex>
            <Url>http://legroom.net/software/uniextract</Url>
            <Name>urlSrc</Name>
          </UrlVariable>
        </value>
      </item>
    </Variables>
    <ExecuteCommand />
    <ExecutePreCommand />
    <ExecuteCommandType>Batch</ExecuteCommandType>
    <ExecutePreCommandType>Batch</ExecutePreCommandType>
    <Category />
    <SourceType>FixedUrl</SourceType>
    <PreviousLocation>F:\exe\uniextract161_noinst.rar</PreviousLocation>
    <DeletePreviousFile>false</DeletePreviousFile>
    <Enabled>true</Enabled>
    <FileHippoId />
    <LastUpdated>2016-02-13T14:11:08.6049833</LastUpdated>
    <TargetPath>{workdir}\</TargetPath>
    <FixedDownloadUrl>{url}</FixedDownloadUrl>
    <Name>uniextract.portable</Name>
  </ApplicationJob>
</Jobs>